{"name": "SERRURE", "shapes": [{"id": 0, "primitives": [{"type": "polygon", "color": 3, "hasAlpha": false, "vertices": [[0, 0], [127, 0], [239, 0], [239, 127], [112, 127], [0, 127]]}, {"type": "polygon", "color": 6, "hasAlpha": false, "vertices": [[116, 21], [116, 104], [95, 104], [73, 82], [73, 43], [95, 21]]}, {"type": "polygon", "color": 5, "hasAlpha": false, "vertices": [[95, 20], [103, 0], [135, 0], [142, 20]]}, {"type": "polygon", "color": 4, "hasAlpha": false, "vertices": [[172, 78], [162, 88], [162, 36], [172, 46]]}, {"type": "polygon", "color": 4, "hasAlpha": false, "vertices": [[73, 42], [94, 0], [103, 0], [97, 17]]}, {"type": "polygon", "color": 4, "hasAlpha": false, "vertices": [[73, 84], [93, 104], [105, 127], [95, 127]]}, {"type": "polygon", "color": 4, "hasAlpha": false, "vertices": [[72, 61], [72, 66], [71, 66], [68, 63], [70, 61]]}, {"type": "polygon", "color": 4, "hasAlpha": false, "vertices": [[67, 48], [77, 38], [77, 88], [75, 88], [67, 80]]}, {"type": "polygon", "color": 3, "hasAlpha": false, "vertices": [[77, 57], [77, 70], [67, 65], [67, 62]]}, {"type": "polygon", "color": 6, "hasAlpha": false, "vertices": [[143, 21], [165, 43], [165, 82], [145, 104], [117, 104], [117, 21]]}, {"type": "polygon", "color": 4, "hasAlpha": false, "vertices": [[143, 20], [136, 0], [144, 0], [172, 45], [165, 42]]}, {"type": "polygon", "color": 4, "hasAlpha": false, "vertices": [[143, 127], [133, 127], [145, 104], [165, 84]]}, {"type": "polygon", "color": 4, "hasAlpha": false, "vertices": [[165, 84], [161, 88], [161, 38], [165, 43]]}, {"type": "polygon", "color": 4, "hasAlpha": false, "vertices": [[168, 61], [170, 63], [167, 66], [166, 66], [166, 61]]}, {"type": "polygon", "color": 3, "hasAlpha": false, "vertices": [[172, 62], [172, 65], [162, 70], [164, 66], [164, 61], [162, 57]]}, {"type": "polygon", "color": 0, "hasAlpha": false, "vertices": [[172, 63], [172, 64], [169, 66], [71, 66], [67, 64], [67, 63], [71, 61], [168, 61]]}, {"type": "polygon", "color": 5, "hasAlpha": false, "vertices": [[95, 105], [143, 105], [132, 127], [106, 127]]}, {"type": "polygon", "color": 12, "hasAlpha": false, "vertices": [[74, 67], [77, 70]]}, {"type": "polygon", "color": 3, "hasAlpha": false, "vertices": [[78, 67], [80, 67], [78, 69]]}, {"type": "polygon", "color": 4, "hasAlpha": false, "vertices": [[78, 57], [161, 57], [160, 60], [81, 60]]}, {"type": "polygon", "color": 7, "hasAlpha": false, "vertices": [[78, 70], [81, 67], [158, 67], [160, 70]]}, {"type": "polygon", "color": 3, "hasAlpha": false, "vertices": [[74, 60], [77, 57], [80, 60]]}, {"type": "polygon", "color": 5, "hasAlpha": false, "vertices": [[81, 67], [78, 70]]}, {"type": "polygon", "color": 3, "hasAlpha": false, "offsetX": 84, "offsetY": 0, "vertices": [[74, 60], [77, 57], [80, 60]]}, {"type": "polygon", "color": 3, "hasAlpha": false, "vertices": [[159, 67], [161, 67], [161, 69]]}, {"type": "polygon", "color": 3, "hasAlpha": false, "vertices": [[160, 69], [160, 67], [161, 67]]}, {"type": "polygon", "color": 3, "hasAlpha": false, "offsetX": 2, "offsetY": 0, "vertices": [[160, 69], [160, 67], [161, 67]]}, {"type": "polygon", "color": 3, "hasAlpha": false, "offsetX": 84, "offsetY": 0, "vertices": [[74, 67], [77, 70]]}, {"type": "polygon", "color": 5, "hasAlpha": false, "offsetX": 83, "offsetY": 0, "vertices": [[74, 67], [77, 70]]}, {"type": "polygon", "color": 0, "hasAlpha": false, "vertices": [[100, 57], [138, 57], [138, 60], [100, 60]]}, {"type": "polygon", "color": 5, "hasAlpha": false, "vertices": [[100, 38], [138, 38], [136, 41], [103, 41]]}, {"type": "polygon", "color": 7, "hasAlpha": false, "vertices": [[103, 56], [100, 56], [100, 39], [103, 42]]}, {"type": "polygon", "color": 4, "hasAlpha": false, "vertices": [[135, 56], [135, 42], [138, 39], [138, 56]]}, {"type": "polygon", "color": 5, "hasAlpha": false, "vertices": [[100, 57], [102, 57], [100, 60]]}, {"type": "polygon", "color": 3, "hasAlpha": false, "offsetX": -23, "offsetY": -10, "vertices": [[159, 67], [161, 67], [161, 69]]}, {"type": "polygon", "color": 3, "hasAlpha": false, "offsetX": 61, "offsetY": -10, "vertices": [[74, 67], [77, 70]]}, {"type": "polygon", "color": 5, "hasAlpha": false, "offsetX": 22, "offsetY": -10, "vertices": [[81, 67], [78, 70]]}, {"type": "polygon", "color": 8, "hasAlpha": false, "vertices": [[104, 42], [134, 42], [134, 56], [104, 56]]}, {"type": "polygon", "color": 10, "hasAlpha": false, "vertices": [[104, 55], [134, 55]]}, {"type": "polygon", "color": 11, "hasAlpha": false, "offsetX": 0, "offsetY": 1, "vertices": [[104, 55], [134, 55]]}, {"type": "polygon", "color": 9, "hasAlpha": false, "offsetX": 0, "offsetY": -1, "vertices": [[104, 55], [134, 55]]}, {"type": "polygon", "color": 9, "hasAlpha": false, "vertices": [[104, 54], [104, 42]]}, {"type": "polygon", "color": 9, "hasAlpha": false, "offsetX": 0, "offsetY": -13, "vertices": [[104, 55], [134, 55]]}, {"type": "polygon", "color": 9, "hasAlpha": false, "vertices": [[134, 42], [134, 53]]}, {"type": "polygon", "color": 15, "hasAlpha": false, "vertices": [[42, 31], [85, 31], [85, 50], [42, 50]]}, {"type": "polygon", "color": 5, "hasAlpha": false, "vertices": [[78, 51], [86, 51]]}, {"type": "polygon", "color": 7, "hasAlpha": false, "vertices": [[86, 31], [86, 49]]}, {"type": "polygon", "color": 2, "hasAlpha": false, "vertices": [[60, 51], [53, 51], [73, 31], [80, 31]]}, {"type": "polygon", "color": 4, "hasAlpha": false, "vertices": [[77, 51], [66, 57], [36, 57], [42, 51]]}, {"type": "polygon", "color": 4, "hasAlpha": false, "vertices": [[36, 56], [36, 26], [41, 31], [41, 51]]}, {"type": "polygon", "color": 5, "hasAlpha": false, "vertices": [[37, 25], [81, 25], [86, 30], [42, 30]]}, {"type": "polygon", "color": 3, "hasAlpha": false, "vertices": [[67, 57], [72, 52], [77, 52]]}, {"type": "polygon", "color": 2, "hasAlpha": false, "vertices": [[44, 50], [42, 50], [42, 45], [56, 31], [63, 31]]}, {"type": "polygon", "color": 2, "hasAlpha": false, "vertices": [[78, 50], [71, 50], [85, 36], [85, 43]]}, {"type": "polygon", "color": 2, "hasAlpha": false, "vertices": [[42, 31], [46, 31], [42, 35]]}, {"type": "polygon", "color": 14, "hasAlpha": false, "vertices": [[47, 31], [42, 36]]}, {"type": "polygon", "color": 14, "hasAlpha": false, "vertices": [[64, 31], [45, 50]]}, {"type": "polygon", "color": 14, "hasAlpha": false, "offsetX": 17, "offsetY": 0, "vertices": [[64, 31], [45, 50]]}, {"type": "polygon", "color": 14, "hasAlpha": false, "vertices": [[85, 44], [79, 50]]}, {"type": "polygon", "color": 7, "hasAlpha": false, "offsetX": -31, "offsetY": -20, "vertices": [[78, 51], [86, 51]]}, {"type": "polygon", "color": 7, "hasAlpha": false, "offsetX": -14, "offsetY": -20, "vertices": [[78, 51], [86, 51]]}, {"type": "polygon", "color": 7, "hasAlpha": false, "vertices": [[82, 31], [86, 31]]}, {"type": "polygon", "color": 3, "hasAlpha": false, "vertices": [[73, 31], [80, 31]]}, {"type": "polygon", "color": 3, "hasAlpha": false, "offsetX": -17, "offsetY": 0, "vertices": [[73, 31], [80, 31]]}, {"type": "polygon", "color": 3, "hasAlpha": false, "offsetX": -40, "offsetY": 0, "vertices": [[82, 31], [86, 31]]}, {"type": "polygon", "color": 5, "hasAlpha": false, "vertices": [[86, 35], [86, 43]]}, {"type": "polygon", "color": 14, "hasAlpha": false, "offsetX": -27, "offsetY": 19, "vertices": [[73, 31], [80, 31]]}, {"type": "polygon", "color": 14, "hasAlpha": false, "offsetX": -10, "offsetY": 19, "vertices": [[73, 31], [80, 31]]}, {"type": "polygon", "color": 14, "hasAlpha": false, "vertices": [[80, 50], [85, 50]]}, {"type": "polygon", "color": 14, "hasAlpha": false, "vertices": [[42, 44], [42, 36]]}, {"type": "polygon", "color": 3, "hasAlpha": false, "vertices": [[77, 51], [41, 51]]}, {"type": "polygon", "color": 3, "hasAlpha": false, "vertices": [[41, 51], [41, 31]]}, {"type": "polygon", "color": 7, "hasAlpha": false, "vertices": [[36, 25], [41, 30]]}, {"type": "polygon", "color": 6, "hasAlpha": false, "vertices": [[36, 26], [40, 30]]}, {"type": "polygon", "color": 6, "hasAlpha": false, "offsetX": 1, "offsetY": 0, "vertices": [[36, 25], [41, 30]]}, {"type": "polygon", "color": 5, "hasAlpha": false, "offsetX": 0, "offsetY": 1, "vertices": [[36, 26], [40, 30]]}, {"type": "polygon", "color": 5, "hasAlpha": false, "vertices": [[40, 31], [40, 34]]}, {"type": "polygon", "color": 3, "hasAlpha": false, "vertices": [[36, 57], [41, 52]]}, {"type": "polygon", "color": 3, "hasAlpha": false, "vertices": [[41, 52], [40, 52]]}, {"type": "polygon", "color": 3, "hasAlpha": false, "vertices": [[40, 52], [36, 56]]}, {"type": "polygon", "color": 0, "hasAlpha": false, "vertices": [[100, 61], [138, 65], [138, 70], [100, 70]]}, {"type": "polygon", "color": 5, "hasAlpha": false, "vertices": [[104, 83], [134, 83], [138, 86], [100, 86]]}, {"type": "polygon", "color": 7, "hasAlpha": false, "vertices": [[103, 81], [100, 85], [100, 71], [103, 71]]}, {"type": "polygon", "color": 4, "hasAlpha": false, "vertices": [[138, 71], [138, 85], [135, 82], [135, 71]]}, {"type": "polygon", "color": 1, "hasAlpha": false, "vertices": [[100, 67], [102, 70], [100, 70]]}, {"type": "polygon", "color": 3, "hasAlpha": false, "vertices": [[138, 68], [138, 70], [136, 70]]}, {"type": "polygon", "color": 3, "hasAlpha": false, "offsetX": 57, "offsetY": 0, "vertices": [[81, 67], [78, 70]]}, {"type": "polygon", "color": 1, "hasAlpha": false, "offsetX": 26, "offsetY": 0, "vertices": [[74, 67], [77, 70]]}, {"type": "polygon", "color": 8, "hasAlpha": false, "vertices": [[104, 71], [134, 71], [134, 82], [104, 82]]}, {"type": "polygon", "color": 10, "hasAlpha": false, "vertices": [[134, 72], [104, 72]]}, {"type": "polygon", "color": 11, "hasAlpha": false, "offsetX": 0, "offsetY": -1, "vertices": [[134, 72], [104, 72]]}, {"type": "polygon", "color": 9, "hasAlpha": false, "offsetX": 0, "offsetY": 1, "vertices": [[134, 72], [104, 72]]}, {"type": "polygon", "color": 9, "hasAlpha": false, "offsetX": 62, "offsetY": 37, "vertices": [[42, 44], [42, 36]]}, {"type": "polygon", "color": 9, "hasAlpha": false, "vertices": [[134, 74], [134, 81]]}, {"type": "polygon", "color": 7, "hasAlpha": false, "vertices": [[144, 104], [94, 104]]}, {"type": "polygon", "color": 7, "hasAlpha": false, "vertices": [[94, 104], [78, 88]]}, {"type": "polygon", "color": 7, "hasAlpha": false, "vertices": [[78, 88], [78, 71]]}, {"type": "polygon", "color": 7, "hasAlpha": false, "vertices": [[143, 21], [160, 38]]}, {"type": "polygon", "color": 7, "hasAlpha": false, "offsetX": 74, "offsetY": 7, "vertices": [[86, 31], [86, 49]]}, {"type": "polygon", "color": 7, "hasAlpha": false, "vertices": [[160, 56], [140, 56]]}, {"type": "polygon", "color": 7, "hasAlpha": false, "vertices": [[143, 21], [96, 21]]}, {"type": "polygon", "color": 7, "hasAlpha": false, "vertices": [[96, 21], [87, 30]]}, {"type": "polygon", "color": 6, "hasAlpha": false, "vertices": [[96, 20], [143, 20]]}, {"type": "polygon", "color": 6, "hasAlpha": false, "vertices": [[143, 20], [161, 38]]}, {"type": "polygon", "color": 6, "hasAlpha": false, "offsetX": 75, "offsetY": 7, "vertices": [[86, 31], [86, 49]]}, {"type": "polygon", "color": 6, "hasAlpha": false, "vertices": [[143, 105], [94, 105]]}, {"type": "polygon", "color": 6, "hasAlpha": false, "vertices": [[94, 105], [77, 88]]}, {"type": "polygon", "color": 6, "hasAlpha": false, "offsetX": -1, "offsetY": 0, "vertices": [[78, 88], [78, 71]]}, {"type": "polygon", "color": 7, "hasAlpha": false, "vertices": [[95, 105], [106, 127]]}, {"type": "polygon", "color": 7, "hasAlpha": false, "vertices": [[143, 105], [132, 127]]}, {"type": "polygon", "color": 5, "hasAlpha": false, "vertices": [[143, 106], [133, 127]]}, {"type": "polygon", "color": 5, "hasAlpha": false, "vertices": [[144, 105], [161, 88]]}, {"type": "polygon", "color": 5, "hasAlpha": false, "vertices": [[161, 88], [161, 72]]}, {"type": "polygon", "color": 7, "hasAlpha": false, "vertices": [[144, 104], [160, 88]]}, {"type": "polygon", "color": 7, "hasAlpha": false, "offsetX": 82, "offsetY": 0, "vertices": [[78, 88], [78, 71]]}, {"type": "polygon", "color": 1, "hasAlpha": false, "vertices": [[160, 82], [160, 88]]}, {"type": "polygon", "color": 1, "hasAlpha": false, "vertices": [[160, 88], [153, 95]]}, {"type": "polygon", "color": 1, "hasAlpha": false, "offsetX": 58, "offsetY": 73, "vertices": [[82, 31], [86, 31]]}, {"type": "polygon", "color": 1, "hasAlpha": false, "vertices": [[144, 104], [146, 102]]}, {"type": "polygon", "color": 1, "hasAlpha": false, "vertices": [[147, 67], [156, 67]]}, {"type": "polygon", "color": 1, "hasAlpha": false, "offsetX": 120, "offsetY": 41, "vertices": [[36, 26], [40, 30]]}, {"type": "polygon", "color": 1, "hasAlpha": false, "vertices": [[160, 71], [160, 73]]}, {"type": "polygon", "color": 1, "hasAlpha": false, "vertices": [[140, 21], [143, 21]]}, {"type": "polygon", "color": 1, "hasAlpha": false, "offsetX": 69, "offsetY": -46, "vertices": [[74, 67], [77, 70]]}, {"type": "polygon", "color": 1, "hasAlpha": false, "vertices": [[158, 36], [160, 38]]}, {"type": "polygon", "color": 1, "hasAlpha": false, "offsetX": 120, "offsetY": 7, "vertices": [[40, 31], [40, 34]]}, {"type": "polygon", "color": 1, "hasAlpha": false, "vertices": [[98, 21], [96, 21]]}, {"type": "polygon", "color": 1, "hasAlpha": false, "vertices": [[96, 21], [94, 23]]}, {"type": "polygon", "color": 1, "hasAlpha": false, "vertices": [[160, 52], [160, 56]]}, {"type": "polygon", "color": 1, "hasAlpha": false, "offsetX": 119, "offsetY": 4, "vertices": [[41, 52], [40, 52]]}, {"type": "polygon", "color": 1, "hasAlpha": false, "offsetX": -61, "offsetY": -32, "vertices": [[161, 88], [161, 72]]}, {"type": "polygon", "color": 1, "hasAlpha": false, "vertices": [[100, 74], [100, 70]]}, {"type": "polygon", "color": 1, "hasAlpha": false, "vertices": [[100, 70], [92, 70]]}, {"type": "polygon", "color": 9, "hasAlpha": false, "offsetX": 0, "offsetY": 27, "vertices": [[104, 55], [134, 55]]}, {"type": "polygon", "color": 4, "hasAlpha": false, "offsetX": 61, "offsetY": 16, "vertices": [[74, 67], [77, 70]]}, {"type": "polygon", "color": 6, "hasAlpha": false, "offsetX": 22, "offsetY": 16, "vertices": [[81, 67], [78, 70]]}, {"type": "polygon", "color": 4, "hasAlpha": false, "vertices": [[142, 20], [135, 0]]}, {"type": "polygon", "color": 5, "hasAlpha": false, "vertices": [[86, 29], [97, 18]]}, {"type": "polygon", "color": 6, "hasAlpha": false, "vertices": [[87, 29], [96, 20]]}, {"type": "polygon", "color": 7, "hasAlpha": false, "vertices": [[97, 20], [104, 0]]}, {"type": "polygon", "color": 4, "hasAlpha": false, "vertices": [[14, 0], [15, 0], [15, 78], [14, 77]]}, {"type": "polygon", "color": 4, "hasAlpha": false, "vertices": [[14, 77], [47, 77], [47, 78], [14, 78]]}, {"type": "polygon", "color": 4, "hasAlpha": false, "vertices": [[47, 77], [48, 77], [48, 127], [47, 127]]}, {"type": "polygon", "color": 2, "hasAlpha": false, "vertices": [[16, 0], [17, 0], [17, 76], [16, 76]]}, {"type": "polygon", "color": 2, "hasAlpha": false, "vertices": [[16, 76], [16, 75], [49, 75], [49, 76]]}, {"type": "polygon", "color": 2, "hasAlpha": false, "vertices": [[49, 75], [50, 75], [50, 127], [49, 127]]}, {"type": "ellipse", "color": 4, "hasAlpha": false, "cx": 41, "cy": 84, "rx": 3, "ry": 3}, {"type": "polygon", "color": 5, "hasAlpha": false, "vertices": [[42, 81], [44, 83], [44, 85]]}, {"type": "polygon", "color": 5, "hasAlpha": false, "vertices": [[43, 85], [43, 86], [42, 87], [41, 86]]}, {"type": "polygon", "color": 6, "hasAlpha": false, "offsetX": -116, "offsetY": 45, "vertices": [[158, 36], [160, 38]]}, {"type": "polygon", "color": 6, "hasAlpha": false, "offsetX": -116, "offsetY": 12, "vertices": [[160, 71], [160, 73]]}, {"type": "polygon", "color": 6, "hasAlpha": false, "vertices": [[44, 85], [43, 86]]}, {"type": "polygon", "color": 2, "hasAlpha": false, "vertices": [[205, 0], [206, 0], [206, 127], [205, 126]]}, {"type": "polygon", "color": 4, "hasAlpha": false, "vertices": [[204, 0], [204, 127], [203, 127], [203, 0]]}, {"type": "polygon", "color": 4, "hasAlpha": false, "vertices": [[142, 20], [135, 0]]}, {"type": "ellipse", "color": 5, "hasAlpha": false, "offsetX": 102, "offsetY": -9, "cx": 41, "cy": 84, "rx": 3, "ry": 3}, {"type": "ellipse", "color": 6, "hasAlpha": false, "cx": 144, "cy": 74, "rx": 2, "ry": 2}, {"type": "ellipse", "color": 7, "hasAlpha": false, "cx": 144, "cy": 74, "rx": 1, "ry": 1}, {"type": "point", "color": 1, "hasAlpha": false, "x": 144, "y": 74}, {"type": "ellipse", "color": 5, "hasAlpha": false, "offsetX": 54, "offsetY": -32, "cx": 41, "cy": 84, "rx": 3, "ry": 3}, {"type": "ellipse", "color": 6, "hasAlpha": false, "offsetX": -48, "offsetY": -23, "cx": 144, "cy": 74, "rx": 2, "ry": 2}, {"type": "ellipse", "color": 7, "hasAlpha": false, "offsetX": -48, "offsetY": -23, "cx": 144, "cy": 74, "rx": 1, "ry": 1}, {"type": "point", "color": 1, "hasAlpha": false, "offsetX": -48, "offsetY": -23, "x": 144, "y": 74}, {"type": "ellipse", "color": 5, "hasAlpha": false, "offsetX": 102, "offsetY": -32, "cx": 41, "cy": 84, "rx": 3, "ry": 3}, {"type": "ellipse", "color": 6, "hasAlpha": false, "offsetX": 0, "offsetY": -23, "cx": 144, "cy": 74, "rx": 2, "ry": 2}, {"type": "ellipse", "color": 7, "hasAlpha": false, "offsetX": 0, "offsetY": -23, "cx": 144, "cy": 74, "rx": 1, "ry": 1}, {"type": "point", "color": 1, "hasAlpha": false, "offsetX": 0, "offsetY": -23, "x": 144, "y": 74}, {"type": "ellipse", "color": 5, "hasAlpha": false, "offsetX": 79, "offsetY": 8, "cx": 41, "cy": 84, "rx": 3, "ry": 3}, {"type": "ellipse", "color": 6, "hasAlpha": false, "offsetX": -23, "offsetY": 17, "cx": 144, "cy": 74, "rx": 2, "ry": 2}, {"type": "ellipse", "color": 7, "hasAlpha": false, "offsetX": -23, "offsetY": 17, "cx": 144, "cy": 74, "rx": 1, "ry": 1}, {"type": "point", "color": 1, "hasAlpha": false, "offsetX": -23, "offsetY": 17, "x": 144, "y": 74}, {"type": "ellipse", "color": 5, "hasAlpha": false, "offsetX": 79, "offsetY": -52, "cx": 41, "cy": 84, "rx": 3, "ry": 3}, {"type": "ellipse", "color": 6, "hasAlpha": false, "offsetX": -23, "offsetY": -43, "cx": 144, "cy": 74, "rx": 2, "ry": 2}, {"type": "ellipse", "color": 7, "hasAlpha": false, "offsetX": -23, "offsetY": -43, "cx": 144, "cy": 74, "rx": 1, "ry": 1}, {"type": "point", "color": 1, "hasAlpha": false, "offsetX": -23, "offsetY": -43, "x": 144, "y": 74}, {"type": "ellipse", "color": 5, "hasAlpha": false, "offsetX": 54, "offsetY": -9, "cx": 41, "cy": 84, "rx": 3, "ry": 3}, {"type": "ellipse", "color": 6, "hasAlpha": false, "offsetX": -48, "offsetY": 0, "cx": 144, "cy": 74, "rx": 2, "ry": 2}, {"type": "ellipse", "color": 7, "hasAlpha": false, "offsetX": -48, "offsetY": 0, "cx": 144, "cy": 74, "rx": 1, "ry": 1}, {"type": "point", "color": 1, "hasAlpha": false, "offsetX": -48, "offsetY": 0, "x": 144, "y": 74}, {"type": "polygon", "color": 12, "hasAlpha": false, "vertices": [[14, 79], [37, 79], [33, 97], [31, 83], [26, 82]]}, {"type": "polygon", "color": 12, "hasAlpha": false, "vertices": [[25, 83], [23, 114], [21, 81]]}, {"type": "polygon", "color": 12, "hasAlpha": false, "vertices": [[33, 111], [34, 117], [33, 122]]}, {"type": "polygon", "color": 12, "hasAlpha": false, "vertices": [[172, 80], [172, 99], [170, 86], [167, 85]]}, {"type": "polygon", "color": 12, "hasAlpha": false, "vertices": [[164, 88], [164, 112], [162, 101], [160, 96]]}, {"type": "polygon", "color": 12, "hasAlpha": false, "vertices": [[173, 51], [175, 56], [175, 63], [173, 74]]}, {"type": "polygon", "color": 12, "hasAlpha": false, "vertices": [[192, 0], [192, 26], [189, 6], [184, 1], [180, 0]]}, {"type": "polygon", "color": 12, "hasAlpha": false, "vertices": [[171, 0], [171, 20], [167, 2], [163, 0]]}, {"type": "polygon", "color": 12, "hasAlpha": false, "vertices": [[20, 0], [29, 0], [27, 12], [25, 58], [24, 6], [21, 2]]}, {"type": "polygon", "color": 12, "hasAlpha": false, "vertices": [[207, 0], [212, 0], [212, 26], [210, 39], [207, 55]]}, {"type": "polygon", "color": 12, "hasAlpha": false, "vertices": [[207, 83], [210, 95], [207, 112]]}, {"type": "polygon", "color": 12, "hasAlpha": false, "vertices": [[227, 23], [225, 64], [222, 44], [225, 26]]}, {"type": "polygon", "color": 12, "hasAlpha": false, "vertices": [[69, 84], [74, 89], [73, 111]]}, {"type": "polygon", "color": 7, "hasAlpha": false, "vertices": [[142, 20], [135, 0]]}, {"type": "polygon", "color": 13, "hasAlpha": false, "vertices": [[111, 44], [113, 44], [113, 52], [111, 52]]}, {"type": "polygon", "color": 13, "hasAlpha": false, "vertices": [[111, 44], [118, 44], [118, 45], [111, 45]]}, {"type": "polygon", "color": 13, "hasAlpha": false, "vertices": [[118, 44], [118, 52], [116, 52], [116, 44]]}, {"type": "polygon", "color": 13, "hasAlpha": false, "vertices": [[118, 52], [111, 52], [111, 51], [118, 51]]}, {"type": "polygon", "color": 13, "hasAlpha": false, "offsetX": 10, "offsetY": 0, "vertices": [[111, 44], [113, 44], [113, 52], [111, 52]]}, {"type": "polygon", "color": 13, "hasAlpha": false, "vertices": [[126, 44], [128, 44], [128, 46], [126, 47]]}, {"type": "polygon", "color": 13, "hasAlpha": false, "vertices": [[124, 47], [126, 47], [126, 48], [124, 48]]}, {"type": "polygon", "color": 13, "hasAlpha": false, "vertices": [[126, 49], [128, 50], [128, 52], [126, 52]]}]}, {"id": 1, "primitives": [{"type": "polygon", "color": 4, "hasAlpha": false, "vertices": [[78, 57], [101, 57], [100, 60], [81, 60]]}, {"type": "polygon", "color": 4, "hasAlpha": false, "vertices": [[138, 57], [162, 57], [162, 60], [138, 60]]}, {"type": "polygon", "color": 3, "hasAlpha": false, "vertices": [[77, 57], [76, 60], [71, 60]]}, {"type": "polygon", "color": 3, "hasAlpha": false, "vertices": [[169, 60], [164, 60], [162, 57]]}, {"type": "polygon", "color": 3, "hasAlpha": false, "vertices": [[74, 60], [77, 57], [80, 60]]}, {"type": "polygon", "color": 3, "hasAlpha": false, "offsetX": 84, "offsetY": 0, "vertices": [[74, 60], [77, 57], [80, 60]]}, {"type": "polygon", "color": 5, "hasAlpha": false, "vertices": [[100, 57], [102, 57], [100, 60]]}, {"type": "polygon", "color": 3, "hasAlpha": false, "offsetX": -23, "offsetY": -10, "vertices": [[159, 67], [161, 67], [161, 69]]}, {"type": "polygon", "color": 3, "hasAlpha": false, "offsetX": 61, "offsetY": -10, "vertices": [[74, 67], [77, 70]]}, {"type": "polygon", "color": 5, "hasAlpha": false, "offsetX": 22, "offsetY": -10, "vertices": [[81, 67], [78, 70]]}, {"type": "polygon", "color": 3, "hasAlpha": false, "offsetX": -12, "offsetY": 29, "vertices": [[82, 31], [86, 31]]}]}, {"id": 2, "primitives": [{"type": "polygon", "color": 12, "hasAlpha": false, "vertices": [[145, 42], [152, 42], [142, 60], [131, 64], [125, 64], [121, 62], [121, 59], [140, 44]]}, {"type": "polygon", "color": 15, "hasAlpha": false, "vertices": [[147, 20], [177, 20], [189, 43], [186, 45], [138, 45], [135, 43]]}, {"type": "polygon", "color": 12, "hasAlpha": false, "vertices": [[148, 56], [150, 45], [155, 36], [160, 36], [164, 45], [171, 46], [188, 63], [190, 68], [190, 74], [194, 81], [195, 86], [174, 122], [129, 122], [126, 100], [126, 95], [128, 89]]}, {"type": "polygon", "color": 13, "hasAlpha": false, "vertices": [[169, 52], [169, 47], [173, 47], [175, 50], [172, 50]]}, {"type": "polygon", "color": 13, "hasAlpha": false, "vertices": [[168, 46], [169, 46], [170, 50], [169, 59], [165, 69], [161, 89], [161, 75], [162, 68], [166, 56], [168, 49]]}, {"type": "polygon", "color": 5, "hasAlpha": false, "vertices": [[138, 46], [186, 46], [186, 48], [138, 48]]}, {"type": "polygon", "color": 7, "hasAlpha": false, "vertices": [[159, 22], [176, 22], [179, 29], [157, 29]]}, {"type": "polygon", "color": 8, "hasAlpha": false, "vertices": [[180, 32], [181, 33], [167, 33], [167, 32], [168, 32]]}, {"type": "polygon", "color": 4, "hasAlpha": false, "vertices": [[135, 43], [137, 45], [137, 48], [135, 45]]}, {"type": "polygon", "color": 4, "hasAlpha": false, "vertices": [[189, 43], [189, 45], [187, 48], [187, 45]]}, {"type": "polygon", "color": 8, "hasAlpha": false, "vertices": [[182, 35], [182, 36], [167, 36], [167, 35]]}, {"type": "polygon", "color": 8, "hasAlpha": false, "vertices": [[182, 35], [184, 39], [182, 39], [178, 35]]}, {"type": "polygon", "color": 8, "hasAlpha": false, "vertices": [[181, 39], [184, 39], [180, 41], [179, 40]]}, {"type": "polygon", "color": 8, "hasAlpha": false, "vertices": [[180, 39], [181, 39], [181, 41], [170, 41], [170, 39]]}, {"type": "polygon", "color": 8, "hasAlpha": false, "vertices": [[168, 35], [171, 36], [172, 40], [169, 40], [168, 39], [167, 37]]}, {"type": "polygon", "color": 4, "hasAlpha": false, "vertices": [[159, 22], [162, 22], [163, 24], [163, 26], [161, 29], [157, 29]]}, {"type": "polygon", "color": 6, "hasAlpha": false, "vertices": [[164, 24], [164, 24], [168, 24], [169, 26], [164, 27]]}, {"type": "polygon", "color": 4, "hasAlpha": false, "vertices": [[168, 23], [170, 24], [170, 26], [167, 27]]}, {"type": "point", "color": 5, "hasAlpha": false, "offsetX": 23, "offsetY": -50, "x": 144, "y": 74}, {"type": "point", "color": 5, "hasAlpha": false, "offsetX": 22, "offsetY": -48, "x": 144, "y": 74}, {"type": "polygon", "color": 6, "hasAlpha": false, "vertices": [[150, 22], [153, 22], [147, 42], [142, 42]]}, {"type": "polygon", "color": 15, "hasAlpha": false, "vertices": [[147, 25], [153, 25], [153, 26], [147, 26]]}, {"type": "polygon", "color": 15, "hasAlpha": false, "vertices": [[152, 30], [155, 31], [145, 32], [145, 30]]}, {"type": "polygon", "color": 15, "hasAlpha": false, "vertices": [[141, 36], [149, 36], [149, 37], [141, 37]]}, {"type": "polygon", "color": 6, "hasAlpha": false, "vertices": [[161, 32], [161, 42]]}, {"type": "polygon", "color": 6, "hasAlpha": false, "vertices": [[157, 32], [155, 42]]}, {"type": "polygon", "color": 13, "hasAlpha": false, "vertices": [[144, 55], [146, 57], [130, 65], [124, 65], [122, 63], [124, 64], [127, 64]]}, {"type": "polygon", "color": 12, "hasAlpha": false, "vertices": [[134, 67], [146, 55], [144, 73], [129, 80], [124, 79], [122, 76], [122, 74], [123, 73]]}, {"type": "polygon", "color": 12, "hasAlpha": false, "vertices": [[156, 35], [160, 33], [164, 34], [167, 38], [167, 48], [159, 74], [141, 69], [151, 45]]}, {"type": "polygon", "color": 13, "hasAlpha": false, "vertices": [[185, 70], [186, 68], [186, 63], [183, 58], [189, 64], [190, 69], [190, 77], [188, 83], [181, 103], [171, 108], [180, 87], [184, 75]]}, {"type": "polygon", "color": 13, "hasAlpha": false, "vertices": [[151, 42], [145, 60]]}, {"type": "polygon", "color": 13, "hasAlpha": false, "vertices": [[145, 60], [138, 74]]}, {"type": "polygon", "color": 13, "hasAlpha": false, "offsetX": 75, "offsetY": -4, "vertices": [[80, 50], [85, 50]]}, {"type": "polygon", "color": 13, "hasAlpha": false, "vertices": [[160, 46], [164, 48]]}, {"type": "polygon", "color": 13, "hasAlpha": false, "vertices": [[164, 48], [166, 42]]}, {"type": "polygon", "color": 13, "hasAlpha": false, "vertices": [[166, 42], [166, 39]]}, {"type": "polygon", "color": 13, "hasAlpha": false, "offsetX": 73, "offsetY": 5, "vertices": [[78, 51], [86, 51]]}, {"type": "polygon", "color": 13, "hasAlpha": false, "vertices": [[159, 56], [150, 58]]}, {"type": "polygon", "color": 12, "hasAlpha": false, "vertices": [[114, 150], [126, 127], [130, 113], [174, 122], [168, 150]]}, {"type": "polygon", "color": 13, "hasAlpha": false, "vertices": [[166, 128], [181, 97], [190, 89], [193, 85], [193, 79], [196, 83], [194, 90], [174, 124], [169, 150], [162, 150]]}, {"type": "polygon", "color": 13, "hasAlpha": false, "vertices": [[145, 58], [139, 59], [143, 55], [146, 55]]}, {"type": "polygon", "color": 13, "hasAlpha": false, "vertices": [[142, 51], [143, 54], [144, 54], [142, 55]]}, {"type": "polygon", "color": 13, "hasAlpha": false, "vertices": [[139, 72], [130, 85]]}, {"type": "polygon", "color": 13, "hasAlpha": false, "vertices": [[139, 71], [137, 67], [140, 69]]}, {"type": "polygon", "color": 13, "hasAlpha": false, "vertices": [[122, 76], [126, 78], [130, 78], [137, 74], [133, 79], [130, 80], [126, 80], [122, 77]]}, {"type": "polygon", "color": 13, "hasAlpha": false, "vertices": [[128, 118], [130, 127], [128, 132], [118, 142], [126, 127]]}, {"type": "polygon", "color": 13, "hasAlpha": false, "vertices": [[169, 62], [172, 65], [166, 65]]}, {"type": "polygon", "color": 13, "hasAlpha": false, "vertices": [[167, 65], [170, 67], [166, 65]]}, {"type": "polygon", "color": 12, "hasAlpha": false, "vertices": [[139, 79], [136, 92], [124, 93], [123, 92], [123, 88]]}, {"type": "polygon", "color": 13, "hasAlpha": false, "offsetX": 92, "offsetY": 30, "vertices": [[40, 52], [36, 56]]}, {"type": "polygon", "color": 13, "hasAlpha": false, "offsetX": -35, "offsetY": 22, "vertices": [[160, 71], [160, 73]]}, {"type": "polygon", "color": 13, "hasAlpha": false, "vertices": [[128, 86], [125, 94]]}, {"type": "polygon", "color": 13, "hasAlpha": false, "vertices": [[122, 89], [123, 91], [126, 91], [124, 93], [122, 91]]}, {"type": "polygon", "color": 7, "hasAlpha": false, "vertices": [[168, 41], [169, 41], [170, 45], [168, 45]]}, {"type": "polygon", "color": 4, "hasAlpha": false, "vertices": [[168, 46], [170, 46], [170, 48], [168, 48]]}]}, {"id": 3, "primitives": [{"type": "polygon", "color": 3, "hasAlpha": false, "offsetX": -9, "offsetY": -1, "vertices": [[104, 55], [134, 55]]}, {"type": "polygon", "color": 4, "hasAlpha": false, "vertices": [[94, 55], [126, 55]]}, {"type": "polygon", "color": 5, "hasAlpha": false, "offsetX": 0, "offsetY": 1, "vertices": [[94, 55], [126, 55]]}, {"type": "polygon", "color": 6, "hasAlpha": false, "vertices": [[93, 57], [127, 57]]}, {"type": "polygon", "color": 7, "hasAlpha": false, "offsetX": 0, "offsetY": 1, "vertices": [[93, 57], [127, 57]]}]}, {"id": 4, "primitives": [{"type": "polygon", "color": 10, "hasAlpha": false, "vertices": [[112, 61], [114, 59], [124, 59], [126, 61], [126, 66], [123, 68], [114, 68], [112, 65]]}]}, {"id": 5, "primitives": [{"type": "polygon", "color": 10, "hasAlpha": false, "vertices": [[100, 61], [104, 57], [134, 57], [138, 61], [138, 65], [134, 70], [105, 70], [100, 65]]}, {"type": "polygon", "color": 11, "hasAlpha": false, "vertices": [[98, 61], [99, 61], [99, 66], [98, 66]]}, {"type": "polygon", "color": 11, "hasAlpha": false, "offsetX": 41, "offsetY": 0, "vertices": [[98, 61], [99, 61], [99, 66], [98, 66]]}, {"type": "polygon", "color": 1, "hasAlpha": false, "vertices": [[95, 61], [97, 61], [97, 66], [95, 66]]}, {"type": "polygon", "color": 1, "hasAlpha": false, "offsetX": 46, "offsetY": 0, "vertices": [[95, 61], [97, 61], [97, 66], [95, 66]]}]}, {"id": 6, "primitives": [{"type": "polygon", "color": 10, "hasAlpha": false, "vertices": [[100, 61], [104, 57], [134, 57], [138, 61], [138, 65], [134, 70], [105, 70], [100, 65]]}, {"type": "polygon", "color": 10, "hasAlpha": false, "vertices": [[88, 61], [150, 61], [150, 66], [88, 66]]}, {"type": "polygon", "color": 1, "hasAlpha": false, "vertices": [[75, 61], [82, 61], [82, 66], [75, 66]]}, {"type": "polygon", "color": 1, "hasAlpha": false, "vertices": [[156, 61], [164, 61], [164, 66], [156, 66]]}, {"type": "polygon", "color": 11, "hasAlpha": false, "offsetX": 76, "offsetY": 0, "vertices": [[75, 61], [82, 61], [82, 66], [75, 66]]}, {"type": "polygon", "color": 11, "hasAlpha": false, "vertices": [[81, 61], [87, 61], [87, 66], [81, 66]]}]}], "palettes": [[{"r": 0, "g": 0, "b": 0}, {"r": 238, "g": 238, "b": 238}, {"r": 0, "g": 34, "b": 34}, {"r": 34, "g": 68, "b": 68}, {"r": 68, "g": 102, "b": 102}, {"r": 102, "g": 136, "b": 136}, {"r": 136, "g": 170, "b": 170}, {"r": 170, "g": 204, "b": 204}, {"r": 204, "g": 34, "b": 0}, {"r": 170, "g": 0, "b": 0}, {"r": 136, "g": 0, "b": 0}, {"r": 102, "g": 0, "b": 0}, {"r": 0, "g": 68, "b": 34}, {"r": 204, "g": 34, "b": 0}, {"r": 238, "g": 102, "b": 0}, {"r": 238, "g": 204, "b": 0}], [{"r": 0, "g": 0, "b": 0}, {"r": 238, "g": 238, "b": 238}, {"r": 0, "g": 34, "b": 34}, {"r": 34, "g": 68, "b": 68}, {"r": 68, "g": 102, "b": 102}, {"r": 102, "g": 136, "b": 136}, {"r": 136, "g": 170, "b": 170}, {"r": 170, "g": 204, "b": 204}, {"r": 238, "g": 68, "b": 0}, {"r": 204, "g": 34, "b": 0}, {"r": 170, "g": 34, "b": 0}, {"r": 136, "g": 0, "b": 0}, {"r": 0, "g": 68, "b": 34}, {"r": 238, "g": 68, "b": 0}, {"r": 238, "g": 102, "b": 0}, {"r": 238, "g": 204, "b": 0}], [{"r": 0, "g": 0, "b": 0}, {"r": 238, "g": 238, "b": 238}, {"r": 0, "g": 34, "b": 34}, {"r": 34, "g": 68, "b": 68}, {"r": 68, "g": 102, "b": 102}, {"r": 102, "g": 136, "b": 136}, {"r": 136, "g": 170, "b": 170}, {"r": 170, "g": 204, "b": 204}, {"r": 238, "g": 102, "b": 0}, {"r": 238, "g": 68, "b": 0}, {"r": 204, "g": 68, "b": 0}, {"r": 170, "g": 0, "b": 0}, {"r": 0, "g": 68, "b": 34}, {"r": 238, "g": 102, "b": 0}, {"r": 238, "g": 102, "b": 0}, {"r": 238, "g": 204, "b": 0}], [{"r": 0, "g": 0, "b": 0}, {"r": 238, "g": 238, "b": 238}, {"r": 0, "g": 34, "b": 34}, {"r": 34, "g": 68, "b": 68}, {"r": 68, "g": 102, "b": 102}, {"r": 102, "g": 136, "b": 136}, {"r": 136, "g": 170, "b": 170}, {"r": 170, "g": 204, "b": 204}, {"r": 238, "g": 136, "b": 0}, {"r": 238, "g": 102, "b": 0}, {"r": 238, "g": 68, "b": 0}, {"r": 204, "g": 0, "b": 0}, {"r": 0, "g": 68, "b": 34}, {"r": 238, "g": 136, "b": 0}, {"r": 238, "g": 102, "b": 0}, {"r": 238, "g": 204, "b": 0}], [{"r": 0, "g": 0, "b": 0}, {"r": 238, "g": 238, "b": 238}, {"r": 0, "g": 34, "b": 34}, {"r": 34, "g": 68, "b": 68}, {"r": 68, "g": 102, "b": 102}, {"r": 102, "g": 136, "b": 136}, {"r": 136, "g": 170, "b": 170}, {"r": 170, "g": 204, "b": 204}, {"r": 0, "g": 170, "b": 0}, {"r": 0, "g": 136, "b": 0}, {"r": 0, "g": 102, "b": 0}, {"r": 0, "g": 68, "b": 0}, {"r": 0, "g": 68, "b": 34}, {"r": 0, "g": 238, "b": 0}, {"r": 238, "g": 102, "b": 0}, {"r": 238, "g": 204, "b": 0}], [{"r": 0, "g": 0, "b": 0}, {"r": 0, "g": 68, "b": 0}, {"r": 0, "g": 34, "b": 34}, {"r": 34, "g": 68, "b": 68}, {"r": 68, "g": 102, "b": 102}, {"r": 68, "g": 136, "b": 136}, {"r": 136, "g": 170, "b": 170}, {"r": 170, "g": 204, "b": 204}, {"r": 221, "g": 68, "b": 0}, {"r": 170, "g": 0, "b": 0}, {"r": 0, "g": 204, "b": 0}, {"r": 0, "g": 136, "b": 0}, {"r": 204, "g": 136, "b": 102}, {"r": 170, "g": 102, "b": 68}, {"r": 136, "g": 68, "b": 17}, {"r": 238, "g": 238, "b": 238}], [{"r": 0, "g": 204, "b": 153}, {"r": 0, "g": 0, "b": 0}, {"r": 51, "g": 0, "b": 0}, {"r": 17, "g": 0, "b": 102}, {"r": 0, "g": 0, "b": 34}, {"r": 85, "g": 0, "b": 0}, {"r": 51, "g": 0, "b": 68}, {"r": 0, "g": 0, "b": 68}, {"r": 68, "g": 0, "b": 0}, {"r": 85, "g": 0, "b": 68}, {"r": 0, "g": 0, "b": 102}, {"r": 68, "g": 0, "b": 0}, {"r": 119, "g": 0, "b": 68}, {"r": 0, "g": 0, "b": 136}, {"r": 51, "g": 0, "b": 0}, {"r": 153, "g": 0, "b": 102}], [{"r": 0, "g": 0, "b": 170}, {"r": 68, "g": 0, "b": 0}, {"r": 187, "g": 0, "b": 68}, {"r": 0, "g": 0, "b": 204}, {"r": 68, "g": 0, "b": 0}, {"r": 221, "g": 0, "b": 68}, {"r": 0, "g": 0, "b": 238}, {"r": 51, "g": 0, "b": 0}, {"r": 255, "g": 0, "b": 0}, {"r": 0, "g": 17, "b": 0}, {"r": 85, "g": 0, "b": 0}, {"r": 17, "g": 0, "b": 204}, {"r": 0, "g": 17, "b": 34}, {"r": 51, "g": 0, "b": 0}, {"r": 51, "g": 0, "b": 68}, {"r": 0, "g": 17, "b": 68}], [{"r": 119, "g": 0, "b": 0}, {"r": 85, "g": 0, "b": 51}, {"r": 0, "g": 17, "b": 102}, {"r": 85, "g": 136, "b": 0}, {"r": 85, "g": 0, "b": 0}, {"r": 68, "g": 0, "b": 0}, {"r": 0, "g": 0, "b": 51}, {"r": 0, "g": 17, "b": 119}, {"r": 51, "g": 0, "b": 0}, {"r": 136, "g": 0, "b": 51}, {"r": 0, "g": 17, "b": 136}, {"r": 0, "g": 0, "b": 34}, {"r": 0, "g": 0, "b": 0}, {"r": 51, "g": 136, "b": 0}, {"r": 17, "g": 0, "b": 0}, {"r": 68, "g": 0, "b": 0}], [{"r": 0, "g": 0, "b": 51}, {"r": 0, "g": 17, "b": 17}, {"r": 0, "g": 85, "b": 51}, {"r": 0, "g": 0, "b": 0}, {"r": 85, "g": 0, "b": 0}, {"r": 153, "g": 0, "b": 0}, {"r": 0, "g": 17, "b": 170}, {"r": 85, "g": 0, "b": 0}, {"r": 187, "g": 0, "b": 119}, {"r": 0, "g": 17, "b": 204}, {"r": 68, "g": 0, "b": 0}, {"r": 221, "g": 0, "b": 85}, {"r": 0, "g": 17, "b": 119}, {"r": 255, "g": 238, "b": 153}, {"r": 255, "g": 255, "b": 102}, {"r": 51, "g": 136, "b": 0}], [{"r": 17, "g": 0, "b": 0}, {"r": 221, "g": 255, "b": 255}, {"r": 102, "g": 0, "b": 51}, {"r": 0, "g": 17, "b": 102}, {"r": 0, "g": 17, "b": 102}, {"r": 255, "g": 255, "b": 102}, {"r": 85, "g": 0, "b": 0}, {"r": 238, "g": 0, "b": 136}, {"r": 0, "g": 17, "b": 255}, {"r": 170, "g": 136, "b": 0}, {"r": 255, "g": 0, "b": 0}, {"r": 0, "g": 0, "b": 0}, {"r": 17, "g": 0, "b": 187}, {"r": 0, "g": 17, "b": 255}, {"r": 0, "g": 0, "b": 0}, {"r": 255, "g": 255, "b": 255}], [{"r": 153, "g": 0, "b": 0}, {"r": 0, "g": 0, "b": 153}, {"r": 0, "g": 17, "b": 255}, {"r": 0, "g": 0, "b": 0}, {"r": 255, "g": 255, "b": 51}, {"r": 153, "g": 0, "b": 0}, {"r": 17, "g": 0, "b": 153}, {"r": 0, "g": 34, "b": 34}, {"r": 255, "g": 0, "b": 0}, {"r": 51, "g": 0, "b": 85}, {"r": 0, "g": 34, "b": 68}, {"r": 119, "g": 0, "b": 0}, {"r": 85, "g": 0, "b": 34}, {"r": 0, "g": 34, "b": 102}, {"r": 68, "g": 0, "b": 0}, {"r": 119, "g": 0, "b": 68}], [{"r": 0, "g": 34, "b": 136}, {"r": 85, "g": 0, "b": 0}, {"r": 153, "g": 0, "b": 51}, {"r": 0, "g": 34, "b": 170}, {"r": 34, "g": 0, "b": 0}, {"r": 187, "g": 0, "b": 34}, {"r": 0, "g": 34, "b": 204}, {"r": 34, "g": 0, "b": 0}, {"r": 221, "g": 0, "b": 238}, {"r": 0, "g": 34, "b": 238}, {"r": 238, "g": 136, "b": 0}, {"r": 238, "g": 0, "b": 0}, {"r": 17, "g": 0, "b": 0}, {"r": 0, "g": 0, "b": 238}, {"r": 0, "g": 34, "b": 255}, {"r": 238, "g": 136, "b": 0}], [{"r": 51, "g": 255, "b": 255}, {"r": 17, "g": 255, "b": 255}, {"r": 204, "g": 0, "b": 119}, {"r": 0, "g": 34, "b": 51}, {"r": 255, "g": 255, "b": 34}, {"r": 255, "g": 238, "b": 204}, {"r": 119, "g": 0, "b": 0}, {"r": 0, "g": 0, "b": 119}, {"r": 0, "g": 51, "b": 17}, {"r": 51, "g": 136, "b": 0}, {"r": 17, "g": 255, "b": 255}, {"r": 255, "g": 0, "b": 0}, {"r": 0, "g": 0, "b": 51}, {"r": 0, "g": 51, "b": 0}, {"r": 255, "g": 221, "b": 136}, {"r": 0, "g": 0, "b": 0}], [{"r": 51, "g": 0, "b": 0}, {"r": 34, "g": 0, "b": 85}, {"r": 0, "g": 51, "b": 17}, {"r": 255, "g": 238, "b": 85}, {"r": 0, "g": 17, "b": 51}, {"r": 238, "g": 136, "b": 0}, {"r": 17, "g": 255, "b": 255}, {"r": 102, "g": 0, "b": 0}, {"r": 51, "g": 0, "b": 238}, {"r": 0, "g": 51, "b": 51}, {"r": 238, "g": 0, "b": 0}, {"r": 68, "g": 0, "b": 238}, {"r": 0, "g": 51, "b": 85}, {"r": 51, "g": 0, "b": 0}, {"r": 102, "g": 0, "b": 51}, {"r": 0, "g": 51, "b": 119}], [{"r": 119, "g": 0, "b": 0}, {"r": 136, "g": 0, "b": 102}, {"r": 0, "g": 51, "b": 119}, {"r": 0, "g": 0, "b": 17}, {"r": 0, "g": 0, "b": 0}, {"r": 102, "g": 136, "b": 0}, {"r": 136, "g": 0, "b": 0}, {"r": 0, "g": 0, "b": 0}, {"r": 17, "g": 0, "b": 85}, {"r": 0, "g": 51, "b": 153}, {"r": 85, "g": 0, "b": 0}, {"r": 170, "g": 0, "b": 51}, {"r": 0, "g": 51, "b": 187}, {"r": 51, "g": 0, "b": 0}, {"r": 204, "g": 0, "b": 51}, {"r": 0, "g": 51, "b": 221}], [{"r": 0, "g": 0, "b": 0}, {"r": 238, "g": 0, "b": 85}, {"r": 0, "g": 51, "b": 255}, {"r": 119, "g": 0, "b": 0}, {"r": 0, "g": 0, "b": 68}, {"r": 0, "g": 68, "b": 17}, {"r": 17, "g": 0, "b": 0}, {"r": 34, "g": 0, "b": 51}, {"r": 0, "g": 17, "b": 102}, {"r": 0, "g": 51, "b": 153}, {"r": 0, "g": 0, "b": 0}, {"r": 51, "g": 136, "b": 0}, {"r": 17, "g": 0, "b": 0}, {"r": 170, "g": 0, "b": 0}, {"r": 0, "g": 0, "b": 17}, {"r": 0, "g": 68, "b": 51}], [{"r": 136, "g": 0, "b": 0}, {"r": 68, "g": 0, "b": 170}, {"r": 0, "g": 68, "b": 68}, {"r": 0, "g": 0, "b": 0}, {"r": 255, "g": 255, "b": 255}, {"r": 187, "g": 136, "b": 0}, {"r": 68, "g": 0, "b": 0}, {"r": 0, "g": 0, "b": 0}, {"r": 17, "g": 0, "b": 153}, {"r": 0, "g": 51, "b": 68}, {"r": 0, "g": 51, "b": 238}, {"r": 0, "g": 34, "b": 85}, {"r": 153, "g": 0, "b": 0}, {"r": 85, "g": 0, "b": 153}, {"r": 0, "g": 68, "b": 102}, {"r": 119, "g": 0, "b": 0}], [{"r": 119, "g": 0, "b": 119}, {"r": 0, "g": 68, "b": 136}, {"r": 119, "g": 0, "b": 0}, {"r": 153, "g": 0, "b": 119}, {"r": 0, "g": 34, "b": 68}, {"r": 0, "g": 68, "b": 170}, {"r": 0, "g": 0, "b": 119}, {"r": 119, "g": 0, "b": 0}, {"r": 170, "g": 0, "b": 119}, {"r": 0, "g": 68, "b": 187}, {"r": 119, "g": 0, "b": 0}, {"r": 204, "g": 0, "b": 119}, {"r": 0, "g": 68, "b": 221}, {"r": 102, "g": 0, "b": 0}, {"r": 238, "g": 0, "b": 102}, {"r": 0, "g": 34, "b": 68}], [{"r": 0, "g": 68, "b": 187}, {"r": 0, "g": 0, "b": 119}, {"r": 102, "g": 0, "b": 0}, {"r": 255, "g": 0, "b": 102}, {"r": 0, "g": 85, "b": 0}, {"r": 102, "g": 136, "b": 0}, {"r": 136, "g": 255, "b": 255}, {"r": 255, "g": 0, "b": 0}, {"r": 0, "g": 0, "b": 102}, {"r": 0, "g": 85, "b": 17}, {"r": 119, "g": 0, "b": 0}, {"r": 34, "g": 0, "b": 119}, {"r": 0, "g": 85, "b": 51}, {"r": 85, "g": 0, "b": 0}, {"r": 68, "g": 0, "b": 85}, {"r": 0, "g": 85, "b": 85}], [{"r": 85, "g": 0, "b": 0}, {"r": 102, "g": 0, "b": 119}, {"r": 0, "g": 68, "b": 136}, {"r": 0, "g": 85, "b": 34}, {"r": 0, "g": 0, "b": 0}, {"r": 119, "g": 0, "b": 0}, {"r": 119, "g": 0, "b": 17}, {"r": 0, "g": 85, "b": 136}, {"r": 17, "g": 136, "b": 0}, {"r": 0, "g": 0, "b": 0}, {"r": 170, "g": 0, "b": 0}, {"r": 153, "g": 0, "b": 17}, {"r": 0, "g": 85, "b": 153}, {"r": 17, "g": 0, "b": 0}, {"r": 170, "g": 0, "b": 17}, {"r": 0, "g": 51, "b": 136}], [{"r": 0, "g": 119, "b": 136}, {"r": 0, "g": 34, "b": 153}, {"r": 17, "g": 0, "b": 0}, {"r": 187, "g": 0, "b": 17}, {"r": 0, "g": 85, "b": 204}, {"r": 17, "g": 136, "b": 0}, {"r": 17, "g": 0, "b": 0}, {"r": 85, "g": 255, "b": 255}, {"r": 34, "g": 0, "b": 17}, {"r": 0, "g": 85, "b": 221}, {"r": 17, "g": 136, "b": 0}, {"r": 153, "g": 0, "b": 0}, {"r": 136, "g": 0, "b": 0}, {"r": 119, "g": 0, "b": 17}, {"r": 0, "g": 85, "b": 238}, {"r": 17, "g": 0, "b": 0}], [{"r": 255, "g": 0, "b": 17}, {"r": 0, "g": 102, "b": 0}, {"r": 17, "g": 136, "b": 0}, {"r": 187, "g": 0, "b": 0}, {"r": 119, "g": 0, "b": 0}, {"r": 68, "g": 0, "b": 17}, {"r": 0, "g": 85, "b": 85}, {"r": 255, "g": 204, "b": 51}, {"r": 255, "g": 238, "b": 0}, {"r": 17, "g": 0, "b": 0}, {"r": 17, "g": 0, "b": 17}, {"r": 0, "g": 102, "b": 34}, {"r": 17, "g": 136, "b": 0}, {"r": 255, "g": 0, "b": 0}, {"r": 0, "g": 0, "b": 0}, {"r": 187, "g": 0, "b": 153}], [{"r": 0, "g": 17, "b": 17}, {"r": 0, "g": 51, "b": 221}, {"r": 0, "g": 17, "b": 0}, {"r": 68, "g": 136, "b": 0}, {"r": 102, "g": 0, "b": 0}, {"r": 102, "g": 0, "b": 0}, {"r": 0, "g": 0, "b": 102}, {"r": 0, "g": 102, "b": 51}, {"r": 68, "g": 0, "b": 0}, {"r": 68, "g": 0, "b": 85}, {"r": 0, "g": 102, "b": 85}, {"r": 102, "g": 0, "b": 0}, {"r": 102, "g": 0, "b": 119}, {"r": 0, "g": 102, "b": 119}, {"r": 68, "g": 0, "b": 0}, {"r": 136, "g": 0, "b": 68}], [{"r": 0, "g": 102, "b": 153}, {"r": 68, "g": 0, "b": 0}, {"r": 170, "g": 0, "b": 34}, {"r": 0, "g": 102, "b": 187}, {"r": 34, "g": 0, "b": 0}, {"r": 204, "g": 0, "b": 34}, {"r": 0, "g": 102, "b": 221}, {"r": 68, "g": 0, "b": 0}, {"r": 238, "g": 0, "b": 85}, {"r": 0, "g": 102, "b": 255}, {"r": 85, "g": 136, "b": 0}, {"r": 221, "g": 255, "b": 255}, {"r": 204, "g": 0, "b": 0}, {"r": 221, "g": 0, "b": 102}, {"r": 0, "g": 85, "b": 187}, {"r": 255, "g": 136, "b": 204}], [{"r": 0, "g": 0, "b": 204}, {"r": 102, "g": 0, "b": 0}, {"r": 0, "g": 0, "b": 102}, {"r": 0, "g": 119, "b": 17}, {"r": 34, "g": 0, "b": 0}, {"r": 34, "g": 0, "b": 68}, {"r": 0, "g": 102, "b": 51}, {"r": 68, "g": 136, "b": 0}, {"r": 221, "g": 0, "b": 0}, {"r": 102, "g": 255, "b": 255}, {"r": 119, "g": 0, "b": 85}, {"r": 0, "g": 119, "b": 51}, {"r": 102, "g": 0, "b": 0}, {"r": 68, "g": 0, "b": 119}, {"r": 0, "g": 119, "b": 85}, {"r": 17, "g": 136, "b": 0}], [{"r": 221, "g": 0, "b": 0}, {"r": 102, "g": 255, "b": 255}, {"r": 0, "g": 0, "b": 85}, {"r": 0, "g": 119, "b": 51}, {"r": 255, "g": 221, "b": 0}, {"r": 255, "g": 238, "b": 153}, {"r": 102, "g": 136, "b": 0}, {"r": 68, "g": 255, "b": 255}, {"r": 0, "g": 255, "b": 255}, {"r": 153, "g": 0, "b": 119}, {"r": 0, "g": 119, "b": 85}, {"r": 255, "g": 221, "b": 0}, {"r": 255, "g": 238, "b": 153}, {"r": 17, "g": 136, "b": 0}, {"r": 221, "g": 0, "b": 0}, {"r": 102, "g": 255, "b": 255}], [{"r": 0, "g": 0, "b": 85}, {"r": 0, "g": 119, "b": 51}, {"r": 0, "g": 0, "b": 0}, {"r": 255, "g": 238, "b": 153}, {"r": 102, "g": 136, "b": 0}, {"r": 68, "g": 0, "b": 0}, {"r": 0, "g": 255, "b": 255}, {"r": 153, "g": 0, "b": 119}, {"r": 0, "g": 119, "b": 85}, {"r": 0, "g": 0, "b": 0}, {"r": 255, "g": 238, "b": 153}, {"r": 17, "g": 136, "b": 0}, {"r": 221, "g": 0, "b": 0}, {"r": 255, "g": 0, "b": 0}, {"r": 136, "g": 0, "b": 85}, {"r": 0, "g": 119, "b": 51}], [{"r": 255, "g": 238, "b": 153}, {"r": 0, "g": 17, "b": 17}, {"r": 102, "g": 136, "b": 0}, {"r": 68, "g": 255, "b": 255}, {"r": 153, "g": 0, "b": 0}, {"r": 17, "g": 0, "b": 119}, {"r": 0, "g": 119, "b": 85}, {"r": 255, "g": 238, "b": 153}, {"r": 0, "g": 17, "b": 17}, {"r": 17, "g": 136, "b": 0}, {"r": 221, "g": 0, "b": 0}, {"r": 255, "g": 255, "b": 255}, {"r": 204, "g": 0, "b": 85}, {"r": 0, "g": 119, "b": 51}, {"r": 255, "g": 238, "b": 153}, {"r": 255, "g": 221, "b": 85}], [{"r": 102, "g": 136, "b": 0}, {"r": 68, "g": 255, "b": 255}, {"r": 153, "g": 255, "b": 255}, {"r": 85, "g": 0, "b": 119}, {"r": 0, "g": 119, "b": 85}, {"r": 255, "g": 238, "b": 153}, {"r": 255, "g": 221, "b": 85}, {"r": 17, "g": 136, "b": 0}, {"r": 221, "g": 0, "b": 0}, {"r": 102, "g": 255, "b": 255}, {"r": 119, "g": 0, "b": 85}, {"r": 0, "g": 119, "b": 51}, {"r": 255, "g": 221, "b": 0}, {"r": 0, "g": 0, "b": 0}, {"r": 102, "g": 136, "b": 0}, {"r": 68, "g": 255, "b": 255}], [{"r": 0, "g": 0, "b": 0}, {"r": 0, "g": 0, "b": 119}, {"r": 0, "g": 119, "b": 85}, {"r": 255, "g": 221, "b": 0}, {"r": 0, "g": 0, "b": 0}, {"r": 17, "g": 0, "b": 0}, {"r": 102, "g": 0, "b": 204}, {"r": 0, "g": 119, "b": 119}, {"r": 204, "g": 0, "b": 0}, {"r": 136, "g": 0, "b": 204}, {"r": 0, "g": 119, "b": 153}, {"r": 204, "g": 0, "b": 0}, {"r": 170, "g": 0, "b": 204}, {"r": 0, "g": 119, "b": 187}, {"r": 204, "g": 0, "b": 0}, {"r": 204, "g": 0, "b": 204}], [{"r": 0, "g": 119, "b": 221}, {"r": 204, "g": 0, "b": 0}, {"r": 238, "g": 0, "b": 204}, {"r": 0, "g": 119, "b": 255}, {"r": 204, "g": 0, "b": 0}, {"r": 0, "g": 0, "b": 204}, {"r": 0, "g": 136, "b": 17}, {"r": 204, "g": 0, "b": 0}, {"r": 34, "g": 0, "b": 204}, {"r": 0, "g": 102, "b": 51}, {"r": 119, "g": 0, "b": 0}, {"r": 51, "g": 0, "b": 221}, {"r": 0, "g": 136, "b": 68}, {"r": 221, "g": 0, "b": 0}, {"r": 85, "g": 0, "b": 221}, {"r": 0, "g": 136, "b": 102}], [{"r": 221, "g": 136, "b": 0}, {"r": 51, "g": 0, "b": 0}, {"r": 170, "g": 0, "b": 0}, {"r": 0, "g": 0, "b": 221}, {"r": 0, "g": 136, "b": 119}, {"r": 221, "g": 0, "b": 0}, {"r": 136, "g": 0, "b": 221}, {"r": 0, "g": 136, "b": 153}, {"r": 221, "g": 0, "b": 0}, {"r": 187, "g": 0, "b": 0}, {"r": 170, "g": 0, "b": 68}, {"r": 0, "g": 136, "b": 187}, {"r": 68, "g": 0, "b": 0}, {"r": 204, "g": 0, "b": 51}, {"r": 0, "g": 136, "b": 221}, {"r": 51, "g": 0, "b": 0}], [{"r": 85, "g": 0, "b": 51}, {"r": 0, "g": 17, "b": 85}, {"r": 0, "g": 85, "b": 68}, {"r": 0, "g": 0, "b": 0}, {"r": 51, "g": 0, "b": 0}, {"r": 221, "g": 0, "b": 85}, {"r": 0, "g": 17, "b": 119}, {"r": 255, "g": 238, "b": 153}, {"r": 255, "g": 255, "b": 102}, {"r": 51, "g": 136, "b": 0}, {"r": 17, "g": 0, "b": 0}, {"r": 221, "g": 255, "b": 255}, {"r": 102, "g": 0, "b": 51}, {"r": 0, "g": 17, "b": 102}, {"r": 0, "g": 17, "b": 102}, {"r": 255, "g": 255, "b": 102}], [{"r": 85, "g": 136, "b": 0}, {"r": 0, "g": 255, "b": 255}, {"r": 68, "g": 0, "b": 0}, {"r": 221, "g": 0, "b": 51}, {"r": 0, "g": 51, "b": 119}, {"r": 0, "g": 136, "b": 238}, {"r": 204, "g": 0, "b": 0}, {"r": 255, "g": 0, "b": 255}, {"r": 0, "g": 153, "b": 0}, {"r": 204, "g": 0, "b": 0}, {"r": 17, "g": 0, "b": 221}, {"r": 0, "g": 153, "b": 34}, {"r": 221, "g": 0, "b": 0}, {"r": 51, "g": 0, "b": 85}, {"r": 0, "g": 153, "b": 68}, {"r": 119, "g": 0, "b": 0}], [{"r": 85, "g": 0, "b": 136}, {"r": 0, "g": 153, "b": 102}, {"r": 68, "g": 0, "b": 0}, {"r": 119, "g": 0, "b": 68}, {"r": 0, "g": 153, "b": 136}, {"r": 136, "g": 0, "b": 0}, {"r": 153, "g": 0, "b": 136}, {"r": 0, "g": 153, "b": 170}, {"r": 136, "g": 0, "b": 0}, {"r": 187, "g": 0, "b": 136}, {"r": 0, "g": 153, "b": 204}, {"r": 136, "g": 0, "b": 0}, {"r": 221, "g": 0, "b": 68}, {"r": 0, "g": 153, "b": 238}, {"r": 102, "g": 0, "b": 0}, {"r": 255, "g": 0, "b": 68}], [{"r": 0, "g": 119, "b": 85}, {"r": 0, "g": 17, "b": 119}, {"r": 255, "g": 204, "b": 238}, {"r": 85, "g": 136, "b": 0}, {"r": 85, "g": 0, "b": 0}, {"r": 102, "g": 255, "b": 255}, {"r": 0, "g": 0, "b": 85}, {"r": 0, "g": 170, "b": 0}, {"r": 102, "g": 0, "b": 0}, {"r": 17, "g": 0, "b": 255}, {"r": 0, "g": 170, "b": 34}, {"r": 255, "g": 0, "b": 0}, {"r": 51, "g": 0, "b": 255}, {"r": 0, "g": 170, "b": 68}, {"r": 102, "g": 0, "b": 0}, {"r": 85, "g": 0, "b": 102}], [{"r": 0, "g": 170, "b": 102}, {"r": 221, "g": 0, "b": 0}, {"r": 119, "g": 0, "b": 204}, {"r": 0, "g": 170, "b": 136}, {"r": 204, "g": 0, "b": 0}, {"r": 153, "g": 0, "b": 221}, {"r": 0, "g": 170, "b": 170}, {"r": 221, "g": 0, "b": 0}, {"r": 187, "g": 0, "b": 221}, {"r": 0, "g": 51, "b": 51}, {"r": 0, "g": 68, "b": 187}, {"r": 255, "g": 255, "b": 204}, {"r": 221, "g": 0, "b": 0}, {"r": 204, "g": 0, "b": 221}, {"r": 0, "g": 170, "b": 221}, {"r": 221, "g": 0, "b": 0}], [{"r": 238, "g": 0, "b": 221}, {"r": 0, "g": 34, "b": 51}, {"r": 0, "g": 68, "b": 153}, {"r": 0, "g": 0, "b": 85}, {"r": 221, "g": 0, "b": 0}, {"r": 255, "g": 0, "b": 221}, {"r": 0, "g": 187, "b": 0}, {"r": 204, "g": 0, "b": 0}, {"r": 17, "g": 0, "b": 221}, {"r": 0, "g": 187, "b": 34}, {"r": 221, "g": 0, "b": 0}, {"r": 51, "g": 0, "b": 221}, {"r": 0, "g": 187, "b": 68}, {"r": 221, "g": 0, "b": 0}, {"r": 85, "g": 0, "b": 221}, {"r": 0, "g": 187, "b": 102}], [{"r": 221, "g": 0, "b": 0}, {"r": 119, "g": 0, "b": 221}, {"r": 0, "g": 187, "b": 136}, {"r": 221, "g": 0, "b": 0}, {"r": 153, "g": 0, "b": 221}, {"r": 0, "g": 187, "b": 170}, {"r": 204, "g": 136, "b": 0}, {"r": 204, "g": 0, "b": 0}, {"r": 204, "g": 0, "b": 0}, {"r": 238, "g": 0, "b": 221}, {"r": 0, "g": 85, "b": 187}, {"r": 255, "g": 221, "b": 221}, {"r": 0, "g": 17, "b": 102}, {"r": 221, "g": 0, "b": 0}, {"r": 187, "g": 0, "b": 221}, {"r": 0, "g": 187, "b": 204}], [{"r": 221, "g": 0, "b": 0}, {"r": 221, "g": 0, "b": 119}, {"r": 0, "g": 187, "b": 238}, {"r": 68, "g": 0, "b": 0}, {"r": 85, "g": 136, "b": 0}, {"r": 255, "g": 255, "b": 255}, {"r": 119, "g": 255, "b": 255}, {"r": 255, "g": 0, "b": 51}, {"r": 0, "g": 187, "b": 255}, {"r": 68, "g": 136, "b": 0}, {"r": 255, "g": 0, "b": 0}, {"r": 0, "g": 0, "b": 0}, {"r": 17, "g": 0, "b": 85}, {"r": 0, "g": 204, "b": 0}, {"r": 102, "g": 136, "b": 0}, {"r": 0, "g": 0, "b": 0}], [{"r": 0, "g": 0, "b": 0}, {"r": 17, "g": 0, "b": 119}, {"r": 0, "g": 0, "b": 17}, {"r": 0, "g": 204, "b": 17}, {"r": 170, "g": 0, "b": 0}, {"r": 85, "g": 0, "b": 0}, {"r": 34, "g": 0, "b": 170}, {"r": 0, "g": 204, "b": 51}, {"r": 187, "g": 136, "b": 0}, {"r": 51, "g": 0, "b": 0}, {"r": 153, "g": 0, "b": 0}, {"r": 0, "g": 0, "b": 187}, {"r": 0, "g": 204, "b": 68}, {"r": 17, "g": 136, "b": 0}, {"r": 68, "g": 0, "b": 0}, {"r": 238, "g": 0, "b": 0}]], "script": {"subsceneCount": 1, "baseOffset": 2, "subscenes": [{"id": 0, "offset": 0, "frames": [{"commands": [{"op": "refreshScreen", "clearMode": 4}, {"op": "drawShape", "shapeId": 0, "x": 0, "y": 0}, {"op": "refreshScreen", "clearMode": 0}, {"op": "setPalette", "paletteNum": 0, "bufferNum": 1}, {"op": "setPalette", "paletteNum": 5, "bufferNum": 0}]}, {"commands": [{"op": "markCurPos"}, {"op": "setPalette", "paletteNum": 1, "bufferNum": 1}]}, {"commands": [{"op": "markCurPos"}, {"op": "waitForSync", "frames": 2}, {"op": "setPalette", "paletteNum": 2, "bufferNum": 1}]}, {"commands": [{"op": "markCurPos"}, {"op": "waitForSync", "frames": 2}, {"op": "setPalette", "paletteNum": 3, "bufferNum": 1}]}, {"commands": [{"op": "markCurPos"}, {"op": "waitForSync", "frames": 2}, {"op": "setPalette", "paletteNum": 2, "bufferNum": 1}]}, {"commands": [{"op": "markCurPos"}, {"op": "waitForSync", "frames": 2}, {"op": "setPalette", "paletteNum": 1, "bufferNum": 1}]}, {"commands": [{"op": "markCurPos"}, {"op": "waitForSync", "frames": 2}, {"op": "setPalette", "paletteNum": 0, "bufferNum": 1}]}, {"commands": [{"op": "markCurPos"}, {"op": "waitForSync", "frames": 2}, {"op": "setPalette", "paletteNum": 1, "bufferNum": 1}]}, {"commands": [{"op": "markCurPos"}, {"op": "waitForSync", "frames": 2}, {"op": "setPalette", "paletteNum": 2, "bufferNum": 1}]}, {"commands": [{"op": "markCurPos"}, {"op": "waitForSync", "frames": 2}, {"op": "setPalette", "paletteNum": 3, "bufferNum": 1}]}, {"commands": [{"op": "markCurPos"}, {"op": "waitForSync", "frames": 2}, {"op": "setPalette", "paletteNum": 2, "bufferNum": 1}]}, {"commands": [{"op": "markCurPos"}, {"op": "waitForSync", "frames": 2}, {"op": "setPalette", "paletteNum": 1, "bufferNum": 1}]}, {"commands": [{"op": "markCurPos"}, {"op": "waitForSync", "frames": 2}, {"op": "setPalette", "paletteNum": 0, "bufferNum": 1}]}, {"commands": [{"op": "markCurPos"}, {"op": "waitForSync", "frames": 2}, {"op": "setPalette", "paletteNum": 1, "bufferNum": 1}]}, {"commands": [{"op": "markCurPos"}, {"op": "waitForSync", "frames": 2}, {"op": "setPalette", "paletteNum": 2, "bufferNum": 1}]}, {"commands": [{"op": "markCurPos"}, {"op": "waitForSync", "frames": 2}, {"op": "setPalette", "paletteNum": 3, "bufferNum": 1}]}, {"commands": [{"op": "markCurPos"}, {"op": "waitForSync", "frames": 2}]}, {"commands": [{"op": "markCurPos"}, {"op": "drawShapeScale", "shapeId": 2, "x": -144, "y": 120, "zoom": 150, "originX": 155, "originY": 85}, {"op": "setPalette", "paletteNum": 2, "bufferNum": 1}]}, {"commands": [{"op": "markCurPos"}, {"op": "drawShapeScale", "shapeId": 2, "x": -133, "y": 96, "zoom": 100, "originX": 155, "originY": 85}]}, {"commands": [{"op": "markCurPos"}, {"op": "drawShapeScale", "shapeId": 2, "x": -117, "y": 76, "zoom": 60, "originX": 155, "originY": 85}, {"op": "setPalette", "paletteNum": 1, "bufferNum": 1}]}, {"commands": [{"op": "markCurPos"}, {"op": "drawShapeScale", "shapeId": 2, "x": -101, "y": 57, "zoom": 30, "originX": 155, "originY": 85}]}, {"commands": [{"op": "markCurPos"}, {"op": "drawShapeScale", "shapeId": 2, "x": -85, "y": 45, "zoom": 10, "originX": 155, "originY": 85}, {"op": "setPalette", "paletteNum": 0, "bufferNum": 1}]}, {"commands": [{"op": "markCurPos"}, {"op": "drawShape", "shapeId": 2, "x": -73, "y": 39}, {"op": "drawShape", "shapeId": 3, "x": -21, "y": 5}, {"op": "drawShape", "shapeId": 1, "x": 0, "y": 0}]}, {"commands": [{"op": "markCurPos"}, {"op": "drawShape", "shapeId": 2, "x": -58, "y": 37}, {"op": "drawShape", "shapeId": 3, "x": -6, "y": 3}, {"op": "drawShape", "shapeId": 1, "x": 0, "y": 0}, {"op": "setPalette", "paletteNum": 1, "bufferNum": 1}]}, {"commands": [{"op": "markCurPos"}, {"op": "drawShape", "shapeId": 2, "x": -43, "y": 37}, {"op": "drawShape", "shapeId": 3, "x": 9, "y": 3}, {"op": "drawShape", "shapeId": 1, "x": 0, "y": 0}]}, {"commands": [{"op": "markCurPos"}, {"op": "drawShape", "shapeId": 4, "x": 0, "y": 0}, {"op": "drawShape", "shapeId": 2, "x": -25, "y": 38}, {"op": "drawShape", "shapeId": 3, "x": 27, "y": 4}, {"op": "drawShape", "shapeId": 1, "x": 0, "y": 0}, {"op": "setPalette", "paletteNum": 2, "bufferNum": 1}]}, {"commands": [{"op": "markCurPos"}, {"op": "drawShape", "shapeId": 5, "x": 0, "y": 0}, {"op": "drawShape", "shapeId": 2, "x": -9, "y": 40}, {"op": "drawShape", "shapeId": 3, "x": 43, "y": 6}, {"op": "drawShape", "shapeId": 1, "x": 0, "y": 0}, {"op": "setPalette", "paletteNum": 4, "bufferNum": 1}]}, {"commands": [{"op": "markCurPos"}, {"op": "drawShape", "shapeId": 6, "x": 0, "y": 0}, {"op": "drawShapeScale", "shapeId": 2, "x": 14, "y": 43, "zoom": 10, "originX": 155, "originY": 85}]}, {"commands": [{"op": "markCurPos"}, {"op": "drawShapeScale", "shapeId": 2, "x": 38, "y": 49, "zoom": 30, "originX": 155, "originY": 85}, {"op": "drawShape", "shapeId": 5, "x": 0, "y": 0}]}, {"commands": [{"op": "markCurPos"}, {"op": "drawShape", "shapeId": 2, "x": 64, "y": 47}, {"op": "drawShape", "shapeId": 4, "x": 0, "y": 0}]}, {"commands": [{"op": "markCurPos"}, {"op": "drawShape", "shapeId": 2, "x": 89, "y": 51}]}, {"commands": [{"op": "markCurPos"}, {"op": "drawShape", "shapeId": 2, "x": 100, "y": 63}]}, {"commands": [{"op": "markCurPos"}]}, {"commands": [{"op": "markCurPos"}]}, {"commands": [{"op": "markCurPos"}, {"op": "waitForSync", "frames": 22}]}]}]}}